mdserve/__init__.py
mdserve/__main__.py
mdserve/favicon.ico
mdserve/markdown_server.py
mdserve/schedule_server.py
mdserve/css/markdown.css
mdserve/css/style.css
mdserve/icons/default_file.svg
mdserve/icons/default_folder.svg
mdserve/icons/default_folder_opened.svg
mdserve/icons/default_root_folder.svg
mdserve/icons/default_root_folder_opened.svg
mdserve/icons/file_type_access.svg
mdserve/icons/file_type_access2.svg
mdserve/icons/file_type_actionscript.svg
mdserve/icons/file_type_actionscript2.svg
mdserve/icons/file_type_ada.svg
mdserve/icons/file_type_advpl.svg
mdserve/icons/file_type_affectscript.svg
mdserve/icons/file_type_affinitydesigner.svg
mdserve/icons/file_type_affinityphoto.svg
mdserve/icons/file_type_affinitypublisher.svg
mdserve/icons/file_type_ai.svg
mdserve/icons/file_type_ai2.svg
mdserve/icons/file_type_al.svg
mdserve/icons/file_type_angular.svg
mdserve/icons/file_type_ansible.svg
mdserve/icons/file_type_antlr.svg
mdserve/icons/file_type_anyscript.svg
mdserve/icons/file_type_apache.svg
mdserve/icons/file_type_apex.svg
mdserve/icons/file_type_api_extractor.svg
mdserve/icons/file_type_apib.svg
mdserve/icons/file_type_apib2.svg
mdserve/icons/file_type_apl.svg
mdserve/icons/file_type_applescript.svg
mdserve/icons/file_type_appsemble.svg
mdserve/icons/file_type_appveyor.svg
mdserve/icons/file_type_arduino.svg
mdserve/icons/file_type_asciidoc.svg
mdserve/icons/file_type_asp.svg
mdserve/icons/file_type_aspx.svg
mdserve/icons/file_type_assembly.svg
mdserve/icons/file_type_astro.svg
mdserve/icons/file_type_astroconfig.svg
mdserve/icons/file_type_ats.svg
mdserve/icons/file_type_audio.svg
mdserve/icons/file_type_aurelia.svg
mdserve/icons/file_type_autohotkey.svg
mdserve/icons/file_type_autoit.svg
mdserve/icons/file_type_avif.svg
mdserve/icons/file_type_avro.svg
mdserve/icons/file_type_awk.svg
mdserve/icons/file_type_aws.svg
mdserve/icons/file_type_azure.svg
mdserve/icons/file_type_azurepipelines.svg
mdserve/icons/file_type_babel.svg
mdserve-1.4.4.dist-info/LICENSE
mdserve-1.4.4.dist-info/METADATA
mdserve-1.4.4.dist-info/WHEEL
mdserve-1.4.4.dist-info/entry_points.txt
mdserve-1.4.4.dist-info/top_level.txt
mdserve-1.4.4.dist-info/zip-safe
mdserve-1.4.4.dist-info/RECORD
