Metadata-Version: 2.1
Name: mdserve
Version: 1.4.4
Summary: Markdown server.
Home-page: https://github.com/openjw/mdserve
Author: kingreatwill
Author-email: 350840291@qq.com
License: MIT
Keywords: markdown
Platform: UNKNOWN
Requires-Dist: markdown (>=3.3.3)
Requires-Dist: pymdown-extensions (>=8.0.1)
Requires-Dist: apscheduler (>=3.6.3)
Requires-Dist: gitpython (>=3.1.11)
Requires-Dist: Pygments (>=2.10.0)
